README.rst
setup.py
forever/__init__.py
forever/example.py
forever/run.py
forever.egg-info/PKG-INFO
forever.egg-info/SOURCES.txt
forever.egg-info/dependency_links.txt
forever.egg-info/top_level.txt