Metadata-Version: 2.1
Name: forever
Version: 0.8.26
Summary: Forever: auto restart any script if it stops printing.
Home-page: https://github.com/valency/forever/
Author: Deepera Co., Ltd.
Author-email: yding@deepera.com
License: UNKNOWN
Keywords: forever,logging,auto-restart
Platform: UNKNOWN
